live_pandoc/__init__.py
live_pandoc/main.py
live_pandoc-0.1.1.dist-info/LICENSE
live_pandoc-0.1.1.dist-info/METADATA
live_pandoc-0.1.1.dist-info/WHEEL
live_pandoc-0.1.1.dist-info/entry_points.txt
live_pandoc-0.1.1.dist-info/top_level.txt
live_pandoc-0.1.1.dist-info/RECORD
