Metadata-Version: 2.1
Name: live-pandoc
Version: 0.1.1
Summary: A program for live rendering a pandoc command
Home-page: http://github.com/blockjoe/live-pandoc
Author: blockjoe
Author-email: blockjoe46@gmail.com
License: MIT
Platform: UNKNOWN
Classifier: License :: OSI Approved :: MIT License
Classifier: Programming Language :: Python :: 3
Requires-Dist: watchdog
